[
  {
    "id": "spawn_basic_01",
    "type": "spawn",
    "size": { "x": 16, "z": 16, "y": 8 },
    "doors": {
      "entry": { "x": 8, "y": 0, "z": 0 },
      "exit": { "x": 8, "y": 0, "z": 15 }
    },
    "spawnPoint": { "x": 8, "y": 0, "z": 8 },
    "minFloor": 1,
    "maxFloor": 99,
    "tags": ["basic"]
  },
  {
    "id": "spawn_wide_02",
    "type": "spawn",
    "size": { "x": 24, "z": 16, "y": 8 },
    "doors": {
      "entry": { "x": 12, "y": 0, "z": 0 },
      "exit": { "x": 12, "y": 0, "z": 15 }
    },
    "spawnPoint": { "x": 12, "y": 0, "z": 8 },
    "minFloor": 1,
    "maxFloor": 99,
    "tags": ["wide"]
  },
  {
    "id": "combat_arena_01",
    "type": "combat",
    "size": { "x": 20, "z": 20, "y": 8 },
    "doors": {
      "entry": { "x": 10, "y": 0, "z": 0 },
      "exit": { "x": 10, "y": 0, "z": 19 }
    },
    "mobSpawns": [
      { "x": 5, "y": 0, "z": 10 },
      { "x": 15, "y": 0, "z": 10 },
      { "x": 10, "y": 0, "z": 15 }
    ],
    "minFloor": 1,
    "maxFloor": 99,
    "tags": ["arena", "open"]
  },
  {
    "id": "combat_arena_large_02",
    "type": "combat",
    "size": { "x": 28, "z": 28, "y": 10 },
    "doors": {
      "entry": { "x": 14, "y": 0, "z": 0 },
      "exit": { "x": 14, "y": 0, "z": 27 }
    },
    "mobSpawns": [
      { "x": 7, "y": 0, "z": 10 },
      { "x": 21, "y": 0, "z": 10 },
      { "x": 7, "y": 0, "z": 20 },
      { "x": 21, "y": 0, "z": 20 },
      { "x": 14, "y": 0, "z": 14 }
    ],
    "minFloor": 1,
    "maxFloor": 99,
    "tags": ["arena", "large"]
  },
  {
    "id": "combat_corridor_03",
    "type": "combat",
    "size": { "x": 10, "z": 30, "y": 6 },
    "doors": {
      "entry": { "x": 5, "y": 0, "z": 0 },
      "exit": { "x": 5, "y": 0, "z": 29 }
    },
    "mobSpawns": [
      { "x": 5, "y": 0, "z": 8 },
      { "x": 5, "y": 0, "z": 16 },
      { "x": 5, "y": 0, "z": 24 }
    ],
    "minFloor": 1,
    "maxFloor": 99,
    "tags": ["corridor", "ambush"]
  },
  {
    "id": "combat_pillars_04",
    "type": "combat",
    "size": { "x": 22, "z": 22, "y": 8 },
    "doors": {
      "entry": { "x": 11, "y": 0, "z": 0 },
      "exit": { "x": 11, "y": 0, "z": 21 }
    },
    "mobSpawns": [
      { "x": 5, "y": 0, "z": 5 },
      { "x": 17, "y": 0, "z": 5 },
      { "x": 5, "y": 0, "z": 17 },
      { "x": 17, "y": 0, "z": 17 }
    ],
    "minFloor": 2,
    "maxFloor": 99,
    "tags": ["arena", "cover"]
  },
  {
    "id": "combat_gauntlet_05",
    "type": "combat",
    "size": { "x": 14, "z": 36, "y": 8 },
    "doors": {
      "entry": { "x": 7, "y": 0, "z": 0 },
      "exit": { "x": 7, "y": 0, "z": 35 }
    },
    "mobSpawns": [
      { "x": 7, "y": 0, "z": 6 },
      { "x": 4, "y": 0, "z": 14 },
      { "x": 10, "y": 0, "z": 14 },
      { "x": 7, "y": 0, "z": 22 },
      { "x": 4, "y": 0, "z": 30 },
      { "x": 10, "y": 0, "z": 30 }
    ],
    "minFloor": 3,
    "maxFloor": 99,
    "tags": ["gauntlet", "long"]
  },
  {
    "id": "combat_pit_06",
    "type": "combat",
    "size": { "x": 24, "z": 24, "y": 12 },
    "doors": {
      "entry": { "x": 12, "y": 0, "z": 0 },
      "exit": { "x": 12, "y": 0, "z": 23 }
    },
    "mobSpawns": [
      { "x": 8, "y": 0, "z": 8 },
      { "x": 16, "y": 0, "z": 8 },
      { "x": 8, "y": 0, "z": 16 },
      { "x": 16, "y": 0, "z": 16 },
      { "x": 12, "y": 0, "z": 12 }
    ],
    "minFloor": 4,
    "maxFloor": 99,
    "tags": ["arena", "deep"]
  },
  {
    "id": "exit_basic_01",
    "type": "exit",
    "size": { "x": 16, "z": 20, "y": 8 },
    "doors": {
      "entry": { "x": 8, "y": 0, "z": 0 },
      "exit": { "x": 8, "y": 0, "z": 19 }
    },
    "exitZone": { "x": 6, "z": 17, "width": 4, "depth": 2 },
    "mobSpawns": [
      { "x": 5, "y": 0, "z": 8 },
      { "x": 11, "y": 0, "z": 8 }
    ],
    "minFloor": 1,
    "maxFloor": 99,
    "tags": ["basic"]
  },
  {
    "id": "exit_arena_02",
    "type": "exit",
    "size": { "x": 22, "z": 22, "y": 8 },
    "doors": {
      "entry": { "x": 11, "y": 0, "z": 0 },
      "exit": { "x": 11, "y": 0, "z": 21 }
    },
    "exitZone": { "x": 9, "z": 19, "width": 4, "depth": 2 },
    "mobSpawns": [
      { "x": 6, "y": 0, "z": 8 },
      { "x": 16, "y": 0, "z": 8 },
      { "x": 11, "y": 0, "z": 14 }
    ],
    "minFloor": 1,
    "maxFloor": 99,
    "tags": ["arena"]
  }
]
